ligo/__init__.py
ligo_common-1.0.3.dist-info/METADATA
ligo_common-1.0.3.dist-info/RECORD
ligo_common-1.0.3.dist-info/WHEEL
ligo_common-1.0.3.dist-info/top_level.txt
